MyAddonsForPyrogram/__init__.py
MyAddonsForPyrogram/database/__init__.py
MyAddonsForPyrogram/database/check_mongo.py
MyAddonsForPyrogram/database/db.py
MyAddonsForPyrogram/database/members.py
MyAddonsForPyrogram/enums/__init__.py
MyAddonsForPyrogram/enums/images.py
MyAddonsForPyrogram/enums/texts.py
MyAddonsForPyrogram/functions/__init__.py
MyAddonsForPyrogram/functions/broad.py
MyAddonsForPyrogram/functions/new_member.py
MyAddonsForPyrogram/functions/telegram_api.py
MyAddonsForPyrogram-1.0.1.dist-info/METADATA
MyAddonsForPyrogram-1.0.1.dist-info/WHEEL
MyAddonsForPyrogram-1.0.1.dist-info/top_level.txt
MyAddonsForPyrogram-1.0.1.dist-info/RECORD
