Metadata-Version: 2.1
Name: MyAddonsForPyrogram
Version: 1.0.1
Summary: A simple addon for pyrogram to manage database, broadcast users, send THANKS FOR JOINING msg to new users who has joined through the bot nd to send reaction through bot.
Author: Pʀɪᴍᴇ Hʀɪᴛᴜ
Project-URL: GitHub, https://github.com/Prime-Hritu/MyAddonsForPyrogram
Requires-Dist: pymongo==4.11.2
Requires-Dist: Pyrogram==2.0.106
Requires-Dist: Requests==2.32.3
Requires-Dist: TgCrypto==1.2.3
